pyhydrate/__init__.py
pyhydrate/error_handling.py
pyhydrate/pyhydrate.py
pyhydrate/types.py
pyhydrate/exceptions/__init__.py
pyhydrate/exceptions/access_pattern_warning.py
pyhydrate/exceptions/api_usage_warning.py
pyhydrate/exceptions/format_warning_message.py
pyhydrate/exceptions/pyhydrate_warning.py
pyhydrate/exceptions/type_conversion_warning.py
pyhydrate/notation/__init__.py
pyhydrate/notation/notation_base.py
pyhydrate/notation/notation_dumper.py
pyhydrate/notation/notation_primitive.py
pyhydrate/notation/notation_structures.py
pyhydrate-1.0.9.dist-info/METADATA
pyhydrate-1.0.9.dist-info/WHEEL
pyhydrate-1.0.9.dist-info/top_level.txt
pyhydrate-1.0.9.dist-info/RECORD
