Metadata-Version: 2.4
Name: pyhydrate
Version: 1.0.9
Summary: A JFDI approach that hydrates a Python class to allow dot notation access to the data structures.
Author-email: Michael Flanigan <7891356+mjfii@users.noreply.github.com>
License:                                  Apache License
Classifier: Programming Language :: Python
Classifier: Programming Language :: Python :: 3
Classifier: Programming Language :: Python :: 3.8
Classifier: Programming Language :: Python :: 3.9
Classifier: Programming Language :: Python :: 3.10
Classifier: Programming Language :: Python :: 3.11
Classifier: Programming Language :: Python :: 3.12
Classifier: Intended Audience :: Developers
Classifier: Intended Audience :: Information Technology
Classifier: License :: OSI Approved :: Apache Software License
Classifier: Operating System :: OS Independent
Requires-Python: >=3.8
Requires-Dist: typing-extensions
Requires-Dist: pyyaml
